gg_mcp_os-0.4.0.dist-info/licenses/LICENSE.txt
gg_mcp_os-0.4.0.dist-info/licenses/NOTICE.txt
mcp_server_opensearch/__init__.py
mcp_server_opensearch/__main__.py
mcp_server_opensearch/clusters_information.py
mcp_server_opensearch/stdio_server.py
mcp_server_opensearch/streaming_server.py
opensearch/__init__.py
opensearch/client.py
opensearch/dashboards_client.py
opensearch/diagnostic.py
opensearch/helper.py
tools/__init__.py
tools/tool_filter.py
tools/tool_generator.py
tools/tool_params.py
tools/tools.py
tools/utils.py
gg_mcp_os-0.4.0.dist-info/METADATA
gg_mcp_os-0.4.0.dist-info/WHEEL
gg_mcp_os-0.4.0.dist-info/entry_points.txt
gg_mcp_os-0.4.0.dist-info/top_level.txt
gg_mcp_os-0.4.0.dist-info/RECORD
