Metadata-Version: 2.4
Name: gg_mcp_os
Version: 0.4.0
Summary: OpenSearch MCP Server с поддержкой Dashboards API и диагностикой подключения - расширенный форк с улучшенной обработкой ошибок и 9 инструментами
Author: VladMain
Maintainer: VladMain
License-Expression: Apache-2.0
Project-URL: Homepage, https://github.com/VladMain/opensearch-mcp-server-py
Project-URL: Documentation, https://github.com/VladMain/opensearch-mcp-server-py/blob/main/QUICK_START.md
Project-URL: Source, https://github.com/VladMain/opensearch-mcp-server-py.git
Project-URL: Bug Tracker, https://github.com/VladMain/opensearch-mcp-server-py/issues
Project-URL: Changelog, https://github.com/opensearch-project/opensearch-mcp-server-py/blob/main/CHANGELOG.md
Keywords: opensearch,mcp,ai,assistant,dashboards,search,diagnostic,troubleshooting,connection,error-handling
Classifier: Development Status :: 4 - Beta
Classifier: Intended Audience :: Developers
Classifier: Operating System :: OS Independent
Classifier: Programming Language :: Python :: 3
Classifier: Programming Language :: Python :: 3.10
Classifier: Programming Language :: Python :: 3.11
Classifier: Programming Language :: Python :: 3.12
Classifier: Topic :: Software Development :: Libraries :: Python Modules
Classifier: Topic :: Internet :: WWW/HTTP :: Indexing/Search
Requires-Python: >=3.10
License-File: LICENSE.txt
License-File: NOTICE.txt
Requires-Dist: aiohttp>=3.11.18
Requires-Dist: boto3>=1.38.3
Requires-Dist: mcp[cli]>=1.9.4
Requires-Dist: opensearch-py>=2.8.0
Requires-Dist: pydantic>=2.11.3
Requires-Dist: pyyaml>=6.0.2
Requires-Dist: requests-aws4auth>=1.3.1
Requires-Dist: semver>=3.0.4
Provides-Extra: server
Dynamic: license-file
